Workbook

Sheet Valuation vs Doordash
B4: Methodology | C4: Min Value | D4: Max Value | E4: Spacer | F4: Bar length
B5: 52-Week Trading Range | C5: 0.8 | D5: 1.7 | E5: =C5 -> 0.8 | F5: =D5-C5 -> 0.9
B6: Comparable Analysis (Ebitda) | C6: 1.6 | D6: 2 | E6: =C6 -> 1.6 | F6: =D6-C6 -> 0.4
B7: Comparable Analysis (Revenue) | C7: 2.6 | D7: 3.2 | E7: =C7 -> 2.6 | F7: =D7-C7 -> 0.6
B8: DCF(Bear case) | C8: 1.5 | D8: 1.75 | E8: =C8 -> 1.5 | F8: =D8-C8 -> 0.25
B9: DCF(Base case) | C9: 2.1 | D9: 2.4 | E9: =C9 -> 2.1 | F9: =D9-C9 -> 0.3
B10: Transaction Price (Doordash) | C10: 1.8 | D10: 1.8

Sheet Assumption
A1: Assumptions for Deliveroo
A3: Metrics | B3: Input | C3: Notes
A6: Average Order Value (AOV)(GBP) | B6: 25.1 | C6: Actual 2024 Reported AOV
A7: YoY Growth | B7: 0.03 | C7: Guidance
A8: Take rate | B8: 0.279 | C8: Commission+fees Deliveroo takes
A9: Rider Cost Per order(GBP) | B9: 4.5 | C9: Calculated:(Revenue-gross profit)/Orders
A10: Marketing Cost (CAC)(GBP) | B10: 52 | C10: Cost to acquire new customer
A11: GTV Rate | B11: 0.07
A12: Shares Outstanding | B12: 1702 | C12: (in millions) Fully diluted count
A13: Offer price (Door Dash) | B13: 1.8
A14: Monthly Active Consumers | B14: 7.1M
A15: MAC YoY Growth | B15: 0.04
A16: Order Frequency | B16: 3.5 | C16: 2024
A17: Order Frequency Growth | B17: 0.03
A19: Capex | B19: 0.03 | C19: (2024-2025)
A20: WACC | B20: 0.12 | C20: (High Risk)
A21: Terminal growth | B21: 0.015 | C21: (UK GDP)

Sheet Revenue
A1: Revenue
B3: 2024 | C3: 2025 E | D3: 2026 E | E3: 2027 E | F3: 2028E | G3: 2029 E | H3: 2030 E
A4: Particulars
A6: Revenue
A7: Monthly Active Customer(M) | B7: 7.1 | C7: 7.1 | D7: =C7+(C7*D8) -> 7.384 | E7: =D7+(D7*E8) -> 7.67936 | F7: =E7+(E7*F8) -> 7.9865344 | G7: =F7+(F7*G8) -> 8.2261304 | H7: =G7+(G7*H8) -> 8.4729143
A8: YOY Growth | C8: 0.02 | D8: =Assumption!$B$15 -> 0.04 | E8: =Assumption!$B$15 -> 0.04 | F8: =Assumption!$B$15 -> 0.04 | G8: 0.03 | H8: 0.03
A9: Order Frequency | B9: 3.5 | C9: =B9+(B9*C10) -> 3.605 | D9: =C9+(C9*D10) -> 3.71315 | E9: =D9+(D9*E10) -> 3.8245445 | F9: =E9+(E9*F10) -> 3.9392808 | G9: =F9+(F9*G10) -> 4.0574593 | H9: =G9+(G9*H10) -> 4.179183
A10: YOY Growth | C10: =Assumption!$B$17 -> 0.03 | D10: =Assumption!$B$17 -> 0.03 | E10: =Assumption!$B$17 -> 0.03 | F10: =Assumption!$B$17 -> 0.03 | G10: =Assumption!$B$17 -> 0.03 | H10: =Assumption!$B$17 -> 0.03
A11: Total Orders (M) | B11: 296 | C11: =C7*C9*12 -> 307.146 | D11: =D7*D9*12 -> 329.0148 | E11: =E7*E9*12 -> 352.44065 | F11: =F7*F9*12 -> 377.53442 | G11: =G7*G9*12 -> 400.52627 | H11: =H7*H9*12 -> 424.91832
A12: YOY Growth | C12: =(C11-B11)/B11 -> 0.037655405 | D12: =(D11-C11)/C11 -> 0.0712 | E12: =(E11-D11)/D11 -> 0.0712 | F12: =(F11-E11)/E11 -> 0.0712 | G12: =(G11-F11)/F11 -> 0.0609 | H12: =(H11-G11)/G11 -> 0.0609
A13: AOV | B13: =Assumption!B6 -> 25.1 | C13: =B13+(B13*C14) -> 26.104 | D13: =C13+(C13*D14) -> 27.14816 | E13: =D13+(D13*E14) -> 28.234086 | F13: =E13+(E13*F14) -> 29.50462 | G13: =F13+(F13*G14) -> 30.389759 | H13: =G13+(G13*H14) -> 31.301452
A14: YOY Growth | C14: 0.04 | D14: 0.04 | E14: 0.04 | F14: 0.045 | G14: =Assumption!$B$7 -> 0.03 | H14: =Assumption!$B$7 -> 0.03
A15: GTv | B15: 7434 | C15: =C11*C13 -> 8017.7392 | D15: =D11*D13 -> 8932.1463 | E15: =E11*E13 -> 9950.8397 | F15: =F11*F13 -> 11139.01 | G15: =G11*G13 -> 12171.897 | H15: =H11*H13 -> 13300.56
A16: YOY Growth | C16: =(C15-B15)/B15 -> 0.078522893 | D16: =(D15-C15)/C15 -> 0.114048 | E16: =(E15-D15)/D15 -> 0.114048 | F16: =(F15-E15)/E15 -> 0.119404 | G16: =(G15-F15)/F15 -> 0.092727 | H16: =(H15-G15)/G15 -> 0.092727
A17: Take Rate | B17: =Assumption!$B$8 -> 0.279 | C17: =Assumption!$B$8 -> 0.279 | D17: =Assumption!$B$8 -> 0.279 | E17: =Assumption!$B$8 -> 0.279 | F17: =Assumption!$B$8 -> 0.279 | G17: =Assumption!$B$8 -> 0.279 | H17: =Assumption!$B$8 -> 0.279
A19: Revenue | B19: 2072 | C19: =C15*C17 -> 2236.9492 | D19: =D15*D17 -> 2492.0688 | E19: =E15*E17 -> 2776.2843 | F19: =F15*F17 -> 3107.7837 | G19: =G15*G17 -> 3395.9592 | H19: =H15*H17 -> 3710.8563
A21: Yoy Growth | C21: =(C19-B19)/B19 -> 0.079608703 | D21: =(D19-C19)/C19 -> 0.114048 | E21: =(E19-D19)/D19 -> 0.114048 | F21: =(F19-E19)/E19 -> 0.119404 | G21: =(G19-F19)/F19 -> 0.092727 | H21: =(H19-G19)/G19 -> 0.092727

Sheet Profit and loss Statement
A2: Profit and Loss statement
B3: =Revenue!B3 -> 2024 | C3: =Revenue!C3 -> 2025 E | D3: =Revenue!D3 -> 2026 E | E3: =Revenue!E3 -> 2027 E | F3: =Revenue!F3 -> 2028E | G3: =Revenue!G3 -> 2029 E | H3: 2030 E
A5: Revenue(m) | B5: =Revenue!B19 -> 2072 | C5: =Revenue!C19 -> 2236.9492 | D5: =Revenue!D19 -> 2492.0688 | E5: =Revenue!E19 -> 2776.2843 | F5: =Revenue!F19 -> 3107.7837 | G5: =Revenue!G19 -> 3395.9592 | H5: =Revenue!H19 -> 3710.8563
A6: YoY Growth | C6: =Revenue!C21 -> 0.079608703 | D6: =Revenue!D21 -> 0.114048 | E6: =Revenue!E21 -> 0.114048 | F6: =Revenue!F21 -> 0.119404 | G6: =Revenue!G21 -> 0.092727 | H6: =Revenue!H21 -> 0.092727
A8: COGS
A9: Cost Per Order | B9: 4.41 | C9: =Assumption!$B$9 -> 4.5 | D9: 4.55 | E9: 4.6 | F9: 4.7 | G9: 4.85 | H9: 5
A10: Total Variable Cost | B10: 1257 | C10: =Revenue!C11*'Profit and loss Statement'!C9 -> 1382.157 | D10: =Revenue!D11*'Profit and loss Statement'!D9 -> 1497.0173 | E10: =Revenue!E11*'Profit and loss Statement'!E9 -> 1621.227 | F10: =Revenue!F11*'Profit and loss Statement'!F9 -> 1774.4118 | G10: =Revenue!G11*'Profit and loss Statement'!G9 -> 1942.5524 | H10: =Revenue!H11*'Profit and loss Statement'!H9 -> 2124.5916
A11: Other Direct Cost | B11: 48 | C11: =48+(48*C6) -> 51.821218 | D11: =48+(48*D6) -> 53.474304 | E11: =48+(48*E6) -> 53.474304 | F11: =48+(48*F6) -> 53.731392 | G11: =48+(48*G6) -> 52.450896 | H11: =48+(48*H6) -> 52.450896
A12: Gross Profit | B12: =B5-B10-B11 -> 767 | C12: =C5-C10-C11 -> 802.97101 | D12: =D5-D10-D11 -> 941.5772 | E12: =E5-E10-E11 -> 1101.583 | F12: =F5-F10-F11 -> 1279.6406 | G12: =G5-G10-G11 -> 1400.9559 | H12: =H5-H10-H11 -> 1533.8138
A13: Gross Margin | B13: =B12/B5 -> 0.37017375 | C13: =C12/C5 -> 0.35895809 | D13: =D12/D5 -> 0.37782953 | E13: =E12/E5 -> 0.39678321 | F13: =F12/F5 -> 0.41175341 | G13: =G12/G5 -> 0.41253614 | H13: =H12/H5 -> 0.4133315
A15: Marketing & Overhead | B15: 637 | C15: =C5*C16 -> 659.90002 | D15: =D5*D16 -> 735.1603 | E15: =E5*E16 -> 819.00386 | F15: =F5*F16 -> 885.71836 | G15: =G5*G16 -> 916.90898 | H15: =H5*H16 -> 1001.9312
A16: M&O % of Revenue | B16: =B15/B5 -> 0.30743243 | C16: 0.295 | D16: 0.295 | E16: 0.295 | F16: 0.285 | G16: 0.27 | H16: 0.27
A17: Ebitda | B17: =B12-B15 -> 130 | C17: =C12-C15 -> 143.07099 | D17: =D12-D15 -> 206.41689 | E17: =E12-E15 -> 282.57913 | F17: =F12-F15 -> 393.92219 | G17: =G12-G15 -> 484.04691 | H17: =H12-H15 -> 531.88261
A19: Ebitda Margin (% Of Revenue) | B19: =B17/B5 -> 0.062741313 | C19: =C17/C5 -> 0.063958086 | D19: =D17/D5 -> 0.082829532 | E19: =E17/E5 -> 0.10178321 | F19: =F17/F5 -> 0.12675341 | G19: =G17/G5 -> 0.14253614 | H19: =H17/H5 -> 0.1433315
A21: Depriciation & Amortization(M) | B21: 48 | C21: =C5*C22 -> 51.449832 | D21: =D5*D22 -> 57.317583 | E21: =E5*E22 -> 63.854539 | F21: =F5*F22 -> 71.479026 | G21: =G5*G22 -> 78.107061 | H21: =H5*H22 -> 85.349695
B22: =B21/B5 -> 0.023166023 | C22: 0.023 | D22: 0.023 | E22: 0.023 | F22: 0.023 | G22: 0.023 | H22: 0.023
A23: Ebit | B23: =B17-B21 -> 82 | C23: =C17-C21 -> 91.621159 | D23: =D17-D21 -> 149.09931 | E23: =E17-E21 -> 218.72459 | F23: =F17-F21 -> 322.44316 | G23: =G17-G21 -> 405.93985 | H23: =H17-H21 -> 446.53291
A24: Net Finance income(interest) | B24: 25 | C24: 25 | D24: 25 | E24: 25 | F24: 25 | G24: 25 | H24: 25
A25: PBT | B25: =B23+B24 -> 107 | C25: =C23+C24 -> 116.62116 | D25: =D23+D24 -> 174.09931 | E25: =E23+E24 -> 243.72459 | F25: =F23+F24 -> 347.44316 | G25: =G23+H24 -> 430.93985 | H25: =H23+I24 -> 446.53291
A26: Tax | B26: 12.3 | C26: =C25*C27 -> 13.411433 | D26: =D25*D27 -> 20.021421 | E26: =E25*E27 -> 28.028328 | F26: =F25*F27 -> 39.955964 | G26: =G25*G27 -> 49.558083 | H26: =H25*H27 -> 98.237241
B27: =B26/B25 -> 0.11495327 | C27: 0.115 | D27: 0.115 | E27: 0.115 | F27: 0.115 | G27: 0.115 | H27: 0.22
A28: PAT | B28: =B25-B26 -> 94.7 | C28: =C25-C26 -> 103.20973 | D28: =D25-D26 -> 154.07789 | E28: =E25-E26 -> 215.69627 | F28: =F25-F26 -> 307.4872 | G28: =G25-G26 -> 381.38177 | H28: =H25-H26 -> 348.29567
H29: =H28/H5 -> 0.093858572

Sheet DCF
B2: =Revenue!B3 -> 2024 | C2: =Revenue!C3 -> 2025 E | D2: =Revenue!D3 -> 2026 E | E2: =Revenue!E3 -> 2027 E | F2: =Revenue!F3 -> 2028E | G2: =Revenue!G3 -> 2029 E | H2: 2030 E
A3: EBIT | B3: ='Profit and loss Statement'!B23 -> 82 | C3: ='Profit and loss Statement'!C23 -> 91.621159 | D3: ='Profit and loss Statement'!D23 -> 149.09931 | E3: ='Profit and loss Statement'!E23 -> 218.72459 | F3: ='Profit and loss Statement'!F23 -> 322.44316 | G3: ='Profit and loss Statement'!G23 -> 405.93985 | H3: ='Profit and loss Statement'!H23 -> 446.53291
A5: Ebit(1-tax) | B5: =B3*(1-'Profit and loss Statement'!B27) -> 72.573832 | C5: =C3*(1-'Profit and loss Statement'!C27) -> 81.084725 | D5: =D3*(1-'Profit and loss Statement'!D27) -> 131.95289 | E5: =E3*(1-'Profit and loss Statement'!E27) -> 193.57127 | F5: =F3*(1-'Profit and loss Statement'!F27) -> 285.3622 | G5: =G3*(1-'Profit and loss Statement'!G27) -> 359.25677 | H5: =H3*(1-'Profit and loss Statement'!H27) -> 348.29567
A7: Add:Depriciation | B7: ='Profit and loss Statement'!B21 -> 48 | C7: ='Profit and loss Statement'!C21 -> 51.449832 | D7: ='Profit and loss Statement'!D21 -> 57.317583 | E7: ='Profit and loss Statement'!E21 -> 63.854539 | F7: ='Profit and loss Statement'!F21 -> 71.479026 | G7: ='Profit and loss Statement'!G21 -> 78.107061 | H7: ='Profit and loss Statement'!H21 -> 85.349695
A9: Less:Capex | B9: 23 | C9: =B9+(B9*C10) -> 23.69 | D9: =C9+(C9*D10) -> 24.4007 | E9: =D9+(D9*E10) -> 25.132721 | F9: =E9+(E9*F10) -> 25.886703 | G9: =F9+(F9*G10) -> 26.663304 | H9: =G9+(G9*H10) -> 27.463203
C10: 0.03 | D10: 0.03 | E10: 0.03 | F10: 0.03 | G10: 0.03 | H10: 0.03
A12: FCF | B12: =B5+B7-B9 -> 97.573832 | C12: =C5+C7-C9 -> 108.84456 | D12: =D5+D7-D9 -> 164.86977 | E12: =E5+E7-E9 -> 232.29308 | F12: =F5+F7-F9 -> 330.95452 | G12: =G5+G7-G9 -> 410.70052 | H12: =H5+H7-H9 -> 406.18217
A14: Terminal Value | C14: 0 | D14: 0 | E14: 0 | F14: 0 | G14: 0 | H14: =H12*(1+B19)/(B18-B19) -> 3926.4276
A18: WACC | B18: =Assumption!B20 -> 0.12
A19: TERMINAL VALUE | B19: =Assumption!B21 -> 0.015 | C19: (UK GDP)
J22: WACC
H23: =B36 -> 2.2098569 | I23: 0.1 | J23: 0.11 | K23: 0.12 | L23: 0.13 | M23: 0.14
A24: Method 1:Perpetuity Growth method | H24: 0.01 | I24: 2.5944542 | J24: 2.3500817 | K24: 2.1512351 | L24: 1.986467 | M24: 1.8478572
H25: 0.015 | I25: 2.6913057 | J25: 2.4246223 | K25: 2.2098569 | L25: 2.033398 | M25: 1.8859948
A26: NPV of Explicit Period | B26: =NPV(B18,C12:H12)*(1+B18)^0.5 -> 1103.926 | H26: 0.02 | I26: 2.8002637 | J26: 2.5074452 | K26: 2.2743409 | L26: 2.0845955 | M26: 1.9273106
A27: NpV of Terminal Period | B27: =NPV(B18,C14:H14) -> 1989.2504 | H27: 0.025 | I27: 2.9237494 | J27: 2.6000119 | K27: 2.3456127 | L27: 2.1406689 | M27: 1.972219
H28: 0.035 | I28: 3.2277142 | J28: 2.8221721 | K28: 2.513311 | L28: 2.2705232 | M28: 2.0748669
A29: Enterprise Value | B29: =B26+B27 -> 3093.1765
A31: Add:Cash | B31: 668
A32: Less:Debt | B32: 0
A33: Equity Value | B33: =B29+B31 -> 3761.1765
A35: Share Outstanding | B35: 1702
A36: Intrinsic Value | B36: =B33/B35 -> 2.2098569

Sheet Comparable Analysis
A2: Company | C2: EV/Revenue (2025 E)x | D2: Ev/Ebitda (2025 E)x
A3: Door dash | C3: 3.2 | D3: 22
A4: Uber | C4: 2.8 | D4: 18.5
A5: Just Eat | C5: 0.9 | D5: 8.5
A6: Delivery Hero | C6: 0.8 | D6: 10
A7: Average Mean | C7: =AVERAGE(C3:C6) -> 1.925 | D7: =AVERAGE(D3:D6) -> 14.75
A8: Median | C8: =MEDIAN(C3:C6) -> 1.85 | D8: =MEDIAN(D3:D6) -> 14.25
A10: A. THE Revenue Method
A12: Metrics | B12: Value (GBP)
A14: Deliveroo 2025 Revenue | B14: =Revenue!C19 -> 2236.9492
A15: Peer Median Multiple | B15: =C8 -> 1.85
A16: Implied Enterprise Value | B16: =B14*B15 -> 4138.3561
A17: Add: Cash | B17: 668
A18: Implied Equity Value | B18: =B16+B17 -> 4806.3561
A20: Shares Outstanding | B20: 1702
A21: Implied Share Price | B21: =B18/B20 -> 2.823946
A23: B.THE Ebitda Method
A24: Deliveroo 2025 Ebitda | B24: ='Profit and loss Statement'!$C$17 -> 143.07099
A25: Peer Median Multiple | B25: =D8 -> 14.25
A26: Implied Enterprise Value | B26: =B24*B25 -> 2038.7616
A27: Add:Cash | B27: 668
A28: Implied Equity Value | B28: =B27+B26 -> 2706.7616
A29: Shares Outstanding | B29: 1702
A30: Implied Share Price | B30: =B28/B29 -> 1.5903417
